{
    "name": "deadend",
    "type": "scene",
    "background_color": [0, 0, 0],
    "boundary": [0, 0, 800, 268],
    "soft_boundaries": [],
    "target_offset": [75, 0],
    "sounds": [
        
    ],
    "zones": [
        {
            "name": "right_limit",
            "type": "no_go",
            "affect": ["whitecrow"],
            "forbidden_moves": null,
            "zone": [48, 14, 58, 24]
        },
        {
            "name": "go_to_hill",
            "type": "interaction",
            "affect": ["whitecrow"],
            "scripts": ["sinoc.go_to_hill"],
            "zone": [28, 14, 39, 24]
        }
    ],
    "elements": [
        {
            "name": "background",
            "type": "layer",
            "deph": 0.0,
            "shader": null
        },
        {
            "name": "bg",
            "type": "set_static",
            "file": "deadend/bg.png",
            "position": [0, 0],
            "deph": 0.0,
            "visible": true
        },
        {
            "name": "rocks_right",
            "type": "set_static",
            "file": "deadend/rocks_right.png",
            "position": [476, 12],
            "deph": 0.0,
            "visible": true
        },
        {
            "name": "bodies",
            "type": "set_static",
            "file": "deadend/bodies.png",
            "position": [484, 98],
            "deph": 0.0,
            "visible": true
        },
        {
            "name": "whitecrow",
            "type": "player",
            "block_position": [32, 7],
            "flip": false
        },
        {
            "name": "roof",
            "type": "set_static",
            "file": "deadend/roof.png",
            "position": [191, 0],
            "deph": 0.0,
            "visible": true
        },
        {
            "name": "fg_planks2",
            "type": "set_static",
            "file": "deadend/fg_planks2.png",
            "position": [300, 0],
            "deph": 0.0,
            "visible": true
        },
        {
            "name": "fg_bottom",
            "type": "set_static",
            "file": "deadend/fg_bottom.png",
            "position": [226, 133],
            "deph": 0.0,
            "visible": true
        },
        {
            "name": "fg_planks",
            "type": "set_static",
            "file": "deadend/fg_planks.png",
            "position": [250, 0],
            "deph": 0.0,
            "visible": true
        },
        {
            "name": "left2",
            "type": "set_static",
            "file": "deadend/left2.png",
            "position": [185, 0],
            "deph": 0.0,
            "visible": true
        },
        {
            "name": "left",
            "type": "set_static",
            "file": "deadend/left.png",
            "position": [0, 0],
            "deph": 0.0,
            "visible": true
        }
    ]
}